pyactors/__main__.py
pyactors-0.1.0.dist-info/LICENSE
pyactors-0.1.0.dist-info/METADATA
pyactors-0.1.0.dist-info/WHEEL
pyactors-0.1.0.dist-info/top_level.txt
pyactors-0.1.0.dist-info/RECORD
