Metadata-Version: 2.1
Name: pyactors
Version: 0.1.0
Summary: UNKNOWN
Home-page: http://github.com/DanielSolomon/pyactors
Author: Daniel Solomon
Author-email: DanielSolomon94.ds@gmail.com
License: MIT
Platform: UNKNOWN
Classifier: Programming Language :: Python :: 3
Classifier: License :: OSI Approved :: MIT License
Classifier: Operating System :: OS Independent
Requires-Dist: pydantic
